AITracker/AITrackerModel.py
AITracker/AITrackerNetwork.py
AITracker/DataValidation.py
AITracker/UpdateH5.py
AITracker/__init__.py
AITracker/data/final_numpy_data.h5
AITracker/image_classifier6.model/fingerprint.pb
AITracker/image_classifier6.model/keras_metadata.pb
AITracker/image_classifier6.model/saved_model.pb
AITracker/image_classifier6.model/variables/variables.data-00000-of-00001
AITracker/image_classifier6.model/variables/variables.index
AITracker-0.9.91.dist-info/LICENSE.txt
AITracker-0.9.91.dist-info/METADATA
AITracker-0.9.91.dist-info/WHEEL
AITracker-0.9.91.dist-info/top_level.txt
AITracker-0.9.91.dist-info/RECORD
